{
  "color": {
    "brand": {
      "50": "#F5F9FF",
      "100": "#E0EDFF",
      "200": "#B8D5FF",
      "300": "#8AB6FF",
      "400": "#578DFF",
      "500": "#2F6BFF",
      "600": "#1F4FCC",
      "700": "#173CA3",
      "800": "#102A7A",
      "900": "#0A1C52"
    },
    "neutral": {
      "50": "#F8FAFC",
      "100": "#EEF2F6",
      "200": "#E2E8F0",
      "300": "#CBD5E1",
      "400": "#94A3B8",
      "500": "#64748B",
      "600": "#475569",
      "700": "#334155",
      "800": "#1E293B",
      "900": "#0F172A"
    },
    "accent": {
      "100": "#FDF4FF",
      "200": "#FAE8FF",
      "300": "#F5D0FE",
      "400": "#E879F9",
      "500": "#D946EF",
      "600": "#C026D3",
      "700": "#A21CAF",
      "800": "#86198F",
      "900": "#701A75"
    }
  },
  "typography": {
    "fontFamily": {
      "sans": "'Pretendard Variable', -apple-system, BlinkMacSystemFont, 'Segoe UI', sans-serif",
      "mono": "'JetBrains Mono', 'Fira Code', ui-monospace, SFMono-Regular, Menlo, Monaco, Consolas, 'Liberation Mono', 'Courier New', monospace"
    },
    "fontSize": {
      "xs": "0.75rem",
      "sm": "0.875rem",
      "md": "1rem",
      "lg": "1.25rem",
      "xl": "1.5rem",
      "2xl": "1.875rem",
      "3xl": "2.25rem",
      "4xl": "3rem"
    },
    "lineHeight": {
      "tightest": "1.1",
      "tighter": "1.25",
      "tight": "1.35",
      "normal": "1.5",
      "relaxed": "1.65",
      "loose": "1.8"
    },
    "fontWeight": {
      "light": 300,
      "regular": 400,
      "medium": 500,
      "semibold": 600,
      "bold": 700
    },
    "letterSpacing": {
      "tightest": "-0.02em",
      "tighter": "-0.01em",
      "tight": "-0.005em",
      "normal": "0",
      "wide": "0.02em",
      "wider": "0.05em"
    }
  },
  "component": {
    "button": {
      "radius": "0.75rem",
      "borderWidth": "1px",
      "font": {
        "family": "'Pretendard Variable', -apple-system, BlinkMacSystemFont, 'Segoe UI', sans-serif",
        "weight": 500
      },
      "focus": {
        "outlineWidth": "2px",
        "outlineColor": "#8AB6FF",
        "outlineOffset": "2px",
        "ringSize": "4px",
        "ringColor": "#E0EDFF"
      },
      "disabled": {
        "opacity": 0.6
      },
      "variant": {
        "solid": {
          "primary": {
            "background": "#2F6BFF",
            "foreground": "#F8FAFC",
            "border": "#2F6BFF",
            "backgroundHover": "#1F4FCC",
            "foregroundHover": "#F8FAFC",
            "borderHover": "#1F4FCC",
            "backgroundActive": "#173CA3",
            "foregroundActive": "#F8FAFC",
            "borderActive": "#173CA3"
          },
          "neutral": {
            "background": "#EEF2F6",
            "foreground": "#0F172A",
            "border": "#EEF2F6",
            "backgroundHover": "#E2E8F0",
            "foregroundHover": "#0F172A",
            "borderHover": "#E2E8F0",
            "backgroundActive": "#CBD5E1",
            "foregroundActive": "#0F172A",
            "borderActive": "#CBD5E1"
          },
          "danger": {
            "background": "#D946EF",
            "foreground": "#F8FAFC",
            "border": "#D946EF",
            "backgroundHover": "#C026D3",
            "foregroundHover": "#F8FAFC",
            "borderHover": "#C026D3",
            "backgroundActive": "#A21CAF",
            "foregroundActive": "#F8FAFC",
            "borderActive": "#A21CAF"
          }
        },
        "outline": {
          "primary": {
            "background": "transparent",
            "foreground": "#2F6BFF",
            "border": "#2F6BFF",
            "backgroundHover": "#F5F9FF",
            "foregroundHover": "#1F4FCC",
            "borderHover": "#1F4FCC",
            "backgroundActive": "#E0EDFF",
            "foregroundActive": "#173CA3",
            "borderActive": "#173CA3"
          },
          "neutral": {
            "background": "transparent",
            "foreground": "#EEF2F6",
            "border": "#EEF2F6",
            "backgroundHover": "#F8FAFC",
            "foregroundHover": "#E2E8F0",
            "borderHover": "#E2E8F0",
            "backgroundActive": "#EEF2F6",
            "foregroundActive": "#CBD5E1",
            "borderActive": "#CBD5E1"
          },
          "danger": {
            "background": "transparent",
            "foreground": "#D946EF",
            "border": "#D946EF",
            "backgroundHover": "#FDF4FF",
            "foregroundHover": "#C026D3",
            "borderHover": "#C026D3",
            "backgroundActive": "#FAE8FF",
            "foregroundActive": "#A21CAF",
            "borderActive": "#A21CAF"
          }
        },
        "ghost": {
          "primary": {
            "background": "transparent",
            "foreground": "#2F6BFF",
            "border": "transparent",
            "backgroundHover": "#F5F9FF",
            "foregroundHover": "#1F4FCC",
            "borderHover": "transparent",
            "backgroundActive": "#E0EDFF",
            "foregroundActive": "#173CA3",
            "borderActive": "transparent"
          },
          "neutral": {
            "background": "transparent",
            "foreground": "#EEF2F6",
            "border": "transparent",
            "backgroundHover": "#F8FAFC",
            "foregroundHover": "#E2E8F0",
            "borderHover": "transparent",
            "backgroundActive": "#EEF2F6",
            "foregroundActive": "#CBD5E1",
            "borderActive": "transparent"
          },
          "danger": {
            "background": "transparent",
            "foreground": "#D946EF",
            "border": "transparent",
            "backgroundHover": "#FDF4FF",
            "foregroundHover": "#C026D3",
            "borderHover": "transparent",
            "backgroundActive": "#FAE8FF",
            "foregroundActive": "#A21CAF",
            "borderActive": "transparent"
          }
        }
      },
      "size": {
        "sm": {
          "paddingInline": "0.75rem",
          "paddingBlock": "0.375rem",
          "gap": "0.375rem",
          "fontSize": "0.875rem",
          "lineHeight": "1.5",
          "minHeight": "2.25rem",
          "spinnerSize": "16px"
        },
        "md": {
          "paddingInline": "1rem",
          "paddingBlock": "0.5rem",
          "gap": "0.5rem",
          "fontSize": "1rem",
          "lineHeight": "1.5",
          "minHeight": "2.5rem",
          "spinnerSize": "18px"
        },
        "lg": {
          "paddingInline": "1.25rem",
          "paddingBlock": "0.75rem",
          "gap": "0.75rem",
          "fontSize": "1.25rem",
          "lineHeight": "1.5",
          "minHeight": "3rem",
          "spinnerSize": "20px"
        }
      }
    }
  }
}
